py_utls-0.3.1.dist-info/licenses/LICENSE
pyutls/__init__.py
pyutls/hex.py
pyutls/list.py
pyutls/logger.py
pyutls/number.py
py_utls-0.3.1.dist-info/METADATA
py_utls-0.3.1.dist-info/WHEEL
py_utls-0.3.1.dist-info/top_level.txt
py_utls-0.3.1.dist-info/RECORD
