Metadata-Version: 2.4
Name: py-utls
Version: 0.3.1
Summary: Utilities for Python
Home-page: https://github.com/cyrildever/py-utls
Author: Cyril Dever
Project-URL: Bug Tracker, https://github.com/cyrildever/py-utls/issues
Keywords: python,utils,chunks,flatten,hexadecimal,euclidean division
Classifier: Programming Language :: Python :: 3
Classifier: License :: OSI Approved :: MIT License
Classifier: Operating System :: OS Independent
Requires-Python: >=3.6
License-File: LICENSE
Dynamic: author
Dynamic: classifier
Dynamic: description
Dynamic: description-content-type
Dynamic: home-page
Dynamic: keywords
Dynamic: license-file
Dynamic: project-url
Dynamic: requires-python
Dynamic: summary
